{
    "rsa_keypair" : {
        "generate" : true,
        "e" : 65537
    },
    "padding" : "PKCS1v15",
    "engine" : {
        "r_stress_test_enable" : false,
        "r_use_list_enable" : false,
        "r_use_list" : [],
        "override_best_r" : "",
        "test_iterations" : 1,
        "alt_iterations" : 0,
        "process_min_count" : 2,
        "process_count" : 2,
        "process_scale" : 4,
        "process_max_best_attempts" : 20,
        "process_min_factor" : 3,
        "rabin_exponent" : 3,
        "min_message_trials" : 1,
        "overlap_report_threshold" : 51,
        "reuse_r_candidates" : true,
        "reuse_r_candidates_path" : "r_candidates.csv",
        "reuse_r_candidates_append_only" : false,
        "r_candidate_mode" : "small_primes",
        "r_candidate_small_primes" : [3, 5, 7, 11, 13, 17],
        "r_candidate_small_prime_factors" : 3,
        "combiner_enable" : false,
        "combiner_k_oracles" : 5,
        "combiner_match_probability" : 0.75,
        "combiner_tie_breaker" : true,
        "base_convert" : true,
        "invert_bits" : false,
        "use_rs_decrypt" : true,
        "enciphered_export_enable" : false,
        "message" : {
            "is_random" : true,
            "bits" : 12,
            "fixed_message" : "HeloWrld1234"
        }
    }
}
